lab0/part1/fullAdder.v
module fullAdder(input cin, input a, input b, output s, output cout);
    // FullAdder compute addition of input cin, a and b,
    // then output result to s and carry bit to cout.

    // TODO: implement your fullAdder design here
    wire s1,c1,c2;
    xor(s1,a,b);
    xor(s,s1,cin);
    and(c2,a,b);
    and(c1,s1,cin);
    or(cout,c1,c2);
    // For testbench verifying, do not modify input and output pin

endmodule

lab0/part1/waveform.vcd
$version Generated by VerilatedVcd $end
$timescale 1ps $end

 $scope module TOP $end
  $var wire  1 $ a $end
  $var wire  1 % b $end
  $var wire  1 # cin $end
  $var wire  1 ' cout $end
  $var wire  1 & s $end
  $scope module fullAdder $end
   $var wire  1 $ a $end
   $var wire  1 % b $end
   $var wire  1 ) c1 $end
   $var wire  1 * c2 $end
   $var wire  1 # cin $end
   $var wire  1 ' cout $end
   $var wire  1 & s $end
   $var wire  1 ( s1 $end
  $upscope $end
 $upscope $end
$enddefinitions $end


#0
0#
0$
0%
0&
0'
0(
0)
0*
#1
1#
1&
#2
0#
1%
1(
#3
1#
0&
1'
1)
#4
0#
1$
0%
1&
0'
0)
#5
1#
0&
1'
1)
#6
0#
1%
0(
0)
1*
#7
1#
1&
